websaw/__init__.py
websaw/__main__.py
websaw/cli.py
websaw/error_pages.py
websaw/server_adapters.py
websaw/watcher.py
websaw/core/__init__.py
websaw/core/_core.py
websaw/core/app.py
websaw/core/app_config.py
websaw/core/context.py
websaw/core/core_events.py
websaw/core/exceptions.py
websaw/core/fixture.py
websaw/core/globs.py
websaw/core/install.py
websaw/core/loggers.py
websaw/core/reloader.py
websaw/core/render.py
websaw/core/static_registry.py
websaw/core/utils.py
websaw/fixtures/__init__.py
websaw/fixtures/dal.py
websaw/fixtures/env.py
websaw/fixtures/session.py
websaw/fixtures/template.py
websaw/fixtures/url.py
websaw/fixtures/xauth.py
websaw-0.0.9.dist-info/LICENSE
websaw-0.0.9.dist-info/METADATA
websaw-0.0.9.dist-info/WHEEL
websaw-0.0.9.dist-info/top_level.txt
websaw-0.0.9.dist-info/RECORD
