Metadata-Version: 2.1
Name: websaw
Version: 0.0.9
Summary: websaw - a web framework for rapid development with pleasure
Home-page: https://github.com/valq7711/websaw
Author: Kucherov Valery <valq7711@gmail.com>
Author-email: valq7711@gmail.com
Maintainer: Kucherov Valery <valq7711@gmail.com>
Maintainer-email: valq7711@gmail.com
License: MIT
Keywords: python webapplication
Platform: any
Classifier: Development Status :: 3 - Alpha
Classifier: Environment :: Web Environment
Classifier: Intended Audience :: Developers
Classifier: License :: OSI Approved :: MIT License
Classifier: Operating System :: OS Independent
Classifier: Programming Language :: Python :: 3.7
Classifier: Programming Language :: Python :: 3.8
Classifier: Programming Language :: Python :: 3.9
Classifier: Topic :: Internet :: WWW/HTTP :: HTTP Servers
Classifier: Topic :: Software Development :: Libraries :: Python Modules
Requires-Python: >=3.7
License-File: LICENSE
Requires-Dist: ombott
Requires-Dist: click
Requires-Dist: gunicorn
Requires-Dist: gevent
Requires-Dist: tornado
Requires-Dist: rocket3
Requires-Dist: threadsafevariable
Requires-Dist: pydal
Requires-Dist: pyjwt
Requires-Dist: yatl
Requires-Dist: requests
Requires-Dist: watchgod
Requires-Dist: renoir
Requires-Dist: upytl (>=0.0.3)
